MANIFEST.in
README.md
setup.py
cached_hitcount/__init__.py
cached_hitcount/admin.py
cached_hitcount/decorators.py
cached_hitcount/models.py
cached_hitcount/settings.py
cached_hitcount/tasks.py
cached_hitcount/tests.py
cached_hitcount/urls.py
cached_hitcount/utils.py
cached_hitcount/views.py
cached_hitcount/management/__init__.py
cached_hitcount/management/helpers.py
cached_hitcount/management/commands/__init__.py
cached_hitcount/management/commands/hitcount_clear_hits.py
cached_hitcount/management/commands/hitcount_persist_hits.py
cached_hitcount/management/commands/hitcount_release_lock.py
cached_hitcount/migrations/0001_initial.py
cached_hitcount/migrations/0002_auto__chg_field_hit_added.py
cached_hitcount/migrations/0003_auto__add_index_hit_added.py
cached_hitcount/migrations/__init__.py
cached_hitcount/templates/hitcount_js.html
cached_hitcount/templatetags/__init__.py
cached_hitcount/templatetags/cached_hitcount_tags.py
django_cached_hitcount.egg-info/PKG-INFO
django_cached_hitcount.egg-info/SOURCES.txt
django_cached_hitcount.egg-info/dependency_links.txt
django_cached_hitcount.egg-info/not-zip-safe
django_cached_hitcount.egg-info/requires.txt
django_cached_hitcount.egg-info/top_level.txt