Metadata-Version: 1.1
Name: django-cached-hitcount
Version: 0.3.2
Summary: Basic app that allows you to track the number of hits/views for a particular object.
Home-page: https://github.com/philroche/django-cached-hitcount
Author: Philip Roche
Author-email: phil@philroche,net
License: GPLv3
Keywords: django hit count
Platform: UNKNOWN
Classifier: Development Status :: 4 - Beta
Classifier: Environment :: Plugins
Classifier: Framework :: Django
Classifier: Intended Audience :: Developers
Classifier: Programming Language :: Python
Classifier: Topic :: Software Development :: Libraries :: Python Modules
